secretsmanager/__init__.py
secretsmanager-0.0.1.dist-info/METADATA
secretsmanager-0.0.1.dist-info/WHEEL
secretsmanager-0.0.1.dist-info/top_level.txt
secretsmanager-0.0.1.dist-info/RECORD
