Metadata-Version: 2.1
Name: secretsmanager
Version: 0.0.1
Summary: Used to get AWS by passing Secret name and Region
Home-page: UNKNOWN
Author: Sai Kumar
Author-email: saikumar.p@talentas.in
License: MIT
Platform: UNKNOWN
Classifier: Programming Language :: Python :: 3
Classifier: License :: OSI Approved :: MIT License
Classifier: Operating System :: OS Independent
Requires-Python: >=3.7
